{"cameraMode":{"drawMode":0,"name":"Shaded","section":"Shading Mode"},"sceneLighting":true,"audioPlay":false,"sceneViewState":{"m_AlwaysRefresh":false,"showFog":true,"showSkybox":true,"showFlares":true,"showImageEffects":true,"showParticleSystems":true,"showVisualEffectGraphs":true,"m_FxEnabled":true},"in2DMode":false,"pivot":{"x":18.43464469909668,"y":8.210565567016602,"z":-32.24630355834961},"rotation":{"x":-0.08753499388694763,"y":0.3790303170681,"z":-0.036052849143743518,"w":-0.9205226302146912},"size":14.821694374084473,"orthographic":false}